FluroView/__init__.py
FluroView/bioviz_ImagePanel.py
FluroView/bioviz_multichannel.py
FluroView-0.4.1.dist-info/LICENSE
FluroView-0.4.1.dist-info/METADATA
FluroView-0.4.1.dist-info/WHEEL
FluroView-0.4.1.dist-info/top_level.txt
FluroView-0.4.1.dist-info/RECORD
