Metadata-Version: 2.1
Name: FluroView
Version: 0.4.1
Summary: A Python package for visualization of biological data, similar to how composite images are viewed in ImageJ
Home-page: https://github.com/Elsword016/FluroView
Author: Biswanath Saha
Author-email: bsaha0659@gmail.com
Classifier: Development Status :: 3 - Alpha
Classifier: Intended Audience :: Science/Research
Classifier: License :: OSI Approved :: MIT License
Classifier: Operating System :: OS Independent
Classifier: Programming Language :: Python :: 3
Classifier: Programming Language :: Python :: 3.7
Classifier: Programming Language :: Python :: 3.8
Classifier: Programming Language :: Python :: 3.9
Requires-Python: >=3.7
License-File: LICENSE
Requires-Dist: numpy
Requires-Dist: matplotlib
Requires-Dist: matplotlib-scalebar
